LICENSE.txt
MANIFEST.in
README.md
setup.py
mu/__init__.py
mu/exceptions.py
mu/main.py
mu/units.py
mu/formats/__init__.py
mu/formats/base/__init__.py
mu/formats/base/reader.py
mu/formats/base/writer.py
mu/formats/html/__init__.py
mu/formats/html/common.py
mu/formats/html/reader.py
mu/formats/html/writer.py
mu/formats/md/__init__.py
mu/formats/md/reader.py
mu/formats/md/writer.py
mu/formats/olx/__init__.py
mu/formats/olx/reader.py
mu/formats/olx/writer.py
mu/utils/__init__.py
mu/utils/youtube.py
mu_courses.egg-info/PKG-INFO
mu_courses.egg-info/SOURCES.txt
mu_courses.egg-info/dependency_links.txt
mu_courses.egg-info/entry_points.txt
mu_courses.egg-info/requires.txt
mu_courses.egg-info/top_level.txt
requirements/base.in