Metadata-Version: 2.1
Name: mu-courses
Version: 0.1.1
Summary: Course authoring for humans
Home-page: https://github.com/overhangio/mu/
Author: Overhang.IO
Author-email: contact@overhang.io
License: AGPLv3
Project-URL: Code, https://github.com/overhangio/mu
Project-URL: Issue tracker, https://github.com/overhangio/mu/issues
Platform: UNKNOWN
Classifier: Development Status :: 5 - Production/Stable
Classifier: Intended Audience :: Developers
Classifier: License :: OSI Approved :: GNU Affero General Public License v3
Classifier: Operating System :: OS Independent
Classifier: Programming Language :: Python
Classifier: Programming Language :: Python :: 3.7
Classifier: Programming Language :: Python :: 3.8
Classifier: Programming Language :: Python :: 3.9
Classifier: Programming Language :: Python :: 3.10
Classifier: Programming Language :: Python :: 3.11
Requires-Python: >=3.7
License-File: LICENSE.txt
